declare_config.py
declare_config-1.0.1.dist-info/LICENSE
declare_config-1.0.1.dist-info/METADATA
declare_config-1.0.1.dist-info/WHEEL
declare_config-1.0.1.dist-info/top_level.txt
declare_config-1.0.1.dist-info/RECORD
