Metadata-Version: 2.1
Name: declare-config
Version: 1.0.1
Summary: Declarative configuration settings for Python.
Home-page: https://github.com/HardlyKnowEm/declare_config
Author: Emma Lefavor
Author-email: emma.lefavor@gmail.com
License: MIT
Platform: UNKNOWN
Classifier: License :: OSI Approved :: MIT License
Classifier: Programming Language :: Python
Classifier: Programming Language :: Python :: 3
Classifier: Programming Language :: Python :: 3.7
Classifier: Programming Language :: Python :: Implementation :: CPython
Classifier: Programming Language :: Python :: Implementation :: PyPy
Classifier: Topic :: Software Development :: Libraries
Requires-Python: >=3.7.0
Requires-Dist: pyyaml
